wpair/__init__.py
wpair/__main__.py
wpair/cli.py
wpair/bluetooth/__init__.py
wpair/bluetooth/classic_adapter.py
wpair/core/__init__.py
wpair/core/device.py
wpair/core/exploit.py
wpair/core/scanner.py
wpair/core/vulnerability_tester.py
wpair/crypto/__init__.py
wpair/crypto/aes.py
wpair/crypto/ecdh.py
wpair/database/__init__.py
wpair/database/known_devices.py
wpair/ui/__init__.py
wpair/ui/terminal.py
wpair/utils/__init__.py
wpair/utils/logger.py
wpair/utils/validators.py
wpair-1.0.0.dist-info/licenses/LICENSE
wpair-1.0.0.dist-info/METADATA
wpair-1.0.0.dist-info/WHEEL
wpair-1.0.0.dist-info/entry_points.txt
wpair-1.0.0.dist-info/top_level.txt
wpair-1.0.0.dist-info/RECORD
