Metadata-Version: 2.4
Name: wpair
Version: 1.0.0
Summary: CVE-2025-36911 Fast Pair vulnerability scanner
Author-email: WPair Contributors <info@example.com>
License: Apache-2.0
Project-URL: Homepage, https://github.com/wpair/wpair-cli
Project-URL: Repository, https://github.com/wpair/wpair-cli
Project-URL: Bug Tracker, https://github.com/wpair/wpair-cli/issues
Keywords: bluetooth,security,fast-pair,vulnerability,CVE-2025-36911,penetration-testing
Classifier: Development Status :: 4 - Beta
Classifier: Intended Audience :: Information Technology
Classifier: Topic :: Security
Classifier: Topic :: System :: Networking
Classifier: License :: OSI Approved :: Apache Software License
Classifier: Programming Language :: Python :: 3
Classifier: Programming Language :: Python :: 3.9
Classifier: Programming Language :: Python :: 3.10
Classifier: Programming Language :: Python :: 3.11
Classifier: Programming Language :: Python :: 3.12
Classifier: Operating System :: POSIX :: Linux
Classifier: Operating System :: Microsoft :: Windows
Requires-Python: >=3.9
License-File: LICENSE
Requires-Dist: bleak>=0.21.0
Requires-Dist: cryptography>=41.0.0
Requires-Dist: rich>=13.0.0
Requires-Dist: click>=8.1.0
Requires-Dist: pydantic>=2.0.0
Requires-Dist: loguru>=0.7.0
Provides-Extra: dev
Requires-Dist: pytest>=7.4.0; extra == "dev"
Requires-Dist: pytest-asyncio>=0.21.0; extra == "dev"
Requires-Dist: pytest-cov>=4.1.0; extra == "dev"
Requires-Dist: pytest-mock>=3.11.0; extra == "dev"
Requires-Dist: black>=23.0.0; extra == "dev"
Requires-Dist: mypy>=1.5.0; extra == "dev"
Requires-Dist: ruff>=0.0.290; extra == "dev"
Dynamic: license-file
